jupyterlab_pioneer_custom_event_demo/__init__.py
jupyterlab_pioneer_custom_event_demo/_version.py
jupyterlab_pioneer_custom_event_demo/handlers.py
jupyterlab_pioneer_custom_event_demo/labextension/package.json
jupyterlab_pioneer_custom_event_demo/labextension/static/509.e8b90f66704d7c0bb37f.js
jupyterlab_pioneer_custom_event_demo/labextension/static/728.1986610d31698b8ce0ad.js
jupyterlab_pioneer_custom_event_demo/labextension/static/remoteEntry.ca6ab72193858fbbdd7c.js
jupyterlab_pioneer_custom_event_demo/labextension/static/style.js
jupyterlab_pioneer_custom_event_demo/labextension/static/third-party-licenses.json
jupyterlab_pioneer_custom_event_demo-0.3.0.data/data/etc/jupyter/jupyter_server_config.d/jupyterlab_pioneer_custom_event_demo.json
jupyterlab_pioneer_custom_event_demo-0.3.0.data/data/share/jupyter/labextensions/jupyterlab-pioneer-custom-event-demo/package.json
jupyterlab_pioneer_custom_event_demo-0.3.0.data/data/share/jupyter/labextensions/jupyterlab-pioneer-custom-event-demo/static/509.e8b90f66704d7c0bb37f.js
jupyterlab_pioneer_custom_event_demo-0.3.0.data/data/share/jupyter/labextensions/jupyterlab-pioneer-custom-event-demo/static/728.1986610d31698b8ce0ad.js
jupyterlab_pioneer_custom_event_demo-0.3.0.data/data/share/jupyter/labextensions/jupyterlab-pioneer-custom-event-demo/static/remoteEntry.ca6ab72193858fbbdd7c.js
jupyterlab_pioneer_custom_event_demo-0.3.0.data/data/share/jupyter/labextensions/jupyterlab-pioneer-custom-event-demo/static/style.js
jupyterlab_pioneer_custom_event_demo-0.3.0.data/data/share/jupyter/labextensions/jupyterlab-pioneer-custom-event-demo/static/third-party-licenses.json
jupyterlab_pioneer_custom_event_demo-0.3.0.data/data/share/jupyter/labextensions/jupyterlab-pioneer-custom-event-demo/install.json
jupyterlab_pioneer_custom_event_demo-0.3.0.dist-info/METADATA
jupyterlab_pioneer_custom_event_demo-0.3.0.dist-info/WHEEL
jupyterlab_pioneer_custom_event_demo-0.3.0.dist-info/licenses/LICENSE
jupyterlab_pioneer_custom_event_demo-0.3.0.dist-info/RECORD
