Metadata-Version: 2.4
Name: jupyterlab_pioneer_custom_event_demo
Version: 0.3.0
Dynamic: Keywords
Summary: A JupyterLab extension that generates telemetry data when a user clicks a specific button.
Project-URL: Homepage, https://github.com/educational-technology-collective/jupyterlab-pioneer-custom-event-demo
Project-URL: Bug Tracker, https://github.com/educational-technology-collective/jupyterlab-pioneer-custom-event-demo/issues
Project-URL: Repository, https://github.com/educational-technology-collective/jupyterlab-pioneer-custom-event-demo.git
Author-email: Educational Technology Collective <etc-jupyterlab-telemetry@umich.edu>
License: BSD 3-Clause License
License-File: LICENSE
Classifier: Framework :: Jupyter
Classifier: Framework :: Jupyter :: JupyterLab
Classifier: Framework :: Jupyter :: JupyterLab :: 4
Classifier: Framework :: Jupyter :: JupyterLab :: Extensions
Classifier: Framework :: Jupyter :: JupyterLab :: Extensions :: Prebuilt
Classifier: License :: OSI Approved :: BSD License
Classifier: Programming Language :: Python
Classifier: Programming Language :: Python :: 3
Classifier: Programming Language :: Python :: 3.8
Classifier: Programming Language :: Python :: 3.9
Classifier: Programming Language :: Python :: 3.10
Classifier: Programming Language :: Python :: 3.11
Requires-Python: >=3.8
Requires-Dist: jupyter-server<3,>=2.0.1
Requires-Dist: jupyterlab-pioneer
